example_package_stormedge/__init__.py
example_package_stormedge/example.py
example_package_stormedge/t1.py
example_package_stormedge/t2.py
example_package_stormedge/dasdfads/__init__.py
example_package_stormedge/dasdfads/pp.py
example_package_stormedge-18.0.1.dist-info/LICENSE
example_package_stormedge-18.0.1.dist-info/WHEEL
example_package_stormedge-18.0.1.dist-info/METADATA
example_package_stormedge-18.0.1.dist-info/RECORD
